{
  "best_global_step": null,
  "best_metric": null,
  "best_model_checkpoint": null,
  "epoch": 0.11682242990654206,
  "eval_steps": 500,
  "global_step": 100,
  "is_hyper_param_search": false,
  "is_local_process_zero": true,
  "is_world_process_zero": true,
  "log_history": [
    {
      "clip_ratio/high_max": 0.0,
      "clip_ratio/high_mean": 0.0,
      "clip_ratio/low_mean": 0.0,
      "clip_ratio/low_min": 0.0,
      "clip_ratio/region_mean": 0.0,
      "completions/clipped_ratio": 0.9,
      "completions/max_length": 128.0,
      "completions/max_terminated_length": 61.0,
      "completions/mean_length": 124.2125,
      "completions/mean_terminated_length": 53.49000015258789,
      "completions/min_length": 97.8,
      "completions/min_terminated_length": 46.6,
      "entropy": 1.4185649514198304,
      "epoch": 0.011682242990654205,
      "frac_reward_zero_std": 0.0,
      "grad_norm": 1.640625,
      "learning_rate": 4.91e-05,
      "loss": -0.0143,
      "num_tokens": 83458.0,
      "reward": -9.6625,
      "reward_std": 16.21368432044983,
      "rewards/gameplay_scores/mean": -8.7875,
      "rewards/gameplay_scores/std": 17.26030468940735,
      "rewards/valid_json_reward/mean": -0.875,
      "rewards/valid_json_reward/std": 3.9282414436340334,
      "step": 10
    },
    {
      "clip_ratio/high_max": 0.0,
      "clip_ratio/high_mean": 0.0,
      "clip_ratio/low_mean": 0.0,
      "clip_ratio/low_min": 0.0,
      "clip_ratio/region_mean": 0.0,
      "completions/clipped_ratio": 0.98125,
      "completions/max_length": 128.0,
      "completions/max_terminated_length": 23.8,
      "completions/mean_length": 127.0875,
      "completions/mean_terminated_length": 23.8,
      "completions/min_length": 113.4,
      "completions/min_terminated_length": 23.8,
      "entropy": 1.5355208545923233,
      "epoch": 0.02336448598130841,
      "frac_reward_zero_std": 0.0,
      "grad_norm": 1.8125,
      "learning_rate": 4.8100000000000004e-05,
      "loss": 0.008,
      "num_tokens": 166664.0,
      "reward": -4.225,
      "reward_std": 16.09888563156128,
      "rewards/gameplay_scores/mean": -4.975,
      "rewards/gameplay_scores/std": 17.47765874862671,
      "rewards/valid_json_reward/mean": 0.75,
      "rewards/valid_json_reward/std": 2.93124737739563,
      "step": 20
    },
    {
      "clip_ratio/high_max": 0.0,
      "clip_ratio/high_mean": 0.0,
      "clip_ratio/low_mean": 0.0,
      "clip_ratio/low_min": 0.0,
      "clip_ratio/region_mean": 0.0,
      "completions/clipped_ratio": 0.9875,
      "completions/max_length": 128.0,
      "completions/max_terminated_length": 19.5,
      "completions/mean_length": 127.61875,
      "completions/mean_terminated_length": 19.5,
      "completions/min_length": 121.9,
      "completions/min_terminated_length": 19.5,
      "entropy": 1.6994812548160554,
      "epoch": 0.035046728971962614,
      "frac_reward_zero_std": 0.1,
      "grad_norm": 1.2421875,
      "learning_rate": 4.71e-05,
      "loss": 0.0008,
      "num_tokens": 250195.0,
      "reward": -8.18125,
      "reward_std": 7.767154121398926,
      "rewards/gameplay_scores/mean": -9.11875,
      "rewards/gameplay_scores/std": 8.152782964706422,
      "rewards/valid_json_reward/mean": 0.9375,
      "rewards/valid_json_reward/std": 2.8750216007232665,
      "step": 30
    },
    {
      "clip_ratio/high_max": 0.0,
      "clip_ratio/high_mean": 0.0,
      "clip_ratio/low_mean": 0.0,
      "clip_ratio/low_min": 0.0,
      "clip_ratio/region_mean": 0.0,
      "completions/clipped_ratio": 0.975,
      "completions/max_length": 128.0,
      "completions/max_terminated_length": 37.5,
      "completions/mean_length": 127.14375,
      "completions/mean_terminated_length": 37.5,
      "completions/min_length": 114.3,
      "completions/min_terminated_length": 37.5,
      "entropy": 1.650158366560936,
      "epoch": 0.04672897196261682,
      "frac_reward_zero_std": 0.05,
      "grad_norm": 0.8046875,
      "learning_rate": 4.61e-05,
      "loss": 0.0133,
      "num_tokens": 334074.0,
      "reward": -2.85625,
      "reward_std": 11.295151901245116,
      "rewards/gameplay_scores/mean": -3.66875,
      "rewards/gameplay_scores/std": 12.38880205154419,
      "rewards/valid_json_reward/mean": 0.8125,
      "rewards/valid_json_reward/std": 3.216586637496948,
      "step": 40
    },
    {
      "clip_ratio/high_max": 0.0,
      "clip_ratio/high_mean": 0.0,
      "clip_ratio/low_mean": 0.0,
      "clip_ratio/low_min": 0.0,
      "clip_ratio/region_mean": 0.0,
      "completions/clipped_ratio": 0.9875,
      "completions/max_length": 128.0,
      "completions/max_terminated_length": 22.5,
      "completions/mean_length": 127.80625,
      "completions/mean_terminated_length": 22.5,
      "completions/min_length": 124.9,
      "completions/min_terminated_length": 22.5,
      "entropy": 1.50280764400959,
      "epoch": 0.05841121495327103,
      "frac_reward_zero_std": 0.35,
      "grad_norm": 0.83984375,
      "learning_rate": 4.5100000000000005e-05,
      "loss": -0.0002,
      "num_tokens": 417043.0,
      "reward": -5.2625,
      "reward_std": 9.513494634628296,
      "rewards/gameplay_scores/mean": -6.45,
      "rewards/gameplay_scores/std": 17.569767951965332,
      "rewards/valid_json_reward/mean": 1.1875,
      "rewards/valid_json_reward/std": 2.033456563949585,
      "step": 50
    },
    {
      "clip_ratio/high_max": 0.0,
      "clip_ratio/high_mean": 0.0,
      "clip_ratio/low_mean": 0.0,
      "clip_ratio/low_min": 0.0,
      "clip_ratio/region_mean": 0.0,
      "completions/clipped_ratio": 0.93125,
      "completions/max_length": 128.0,
      "completions/max_terminated_length": 59.7,
      "completions/mean_length": 125.775,
      "completions/mean_terminated_length": 54.516667175292966,
      "completions/min_length": 99.8,
      "completions/min_terminated_length": 48.6,
      "entropy": 1.195768231153488,
      "epoch": 0.07009345794392523,
      "frac_reward_zero_std": 0.55,
      "grad_norm": 0.0,
      "learning_rate": 4.41e-05,
      "loss": -0.0126,
      "num_tokens": 500639.0,
      "reward": 2.925,
      "reward_std": 4.258828115463257,
      "rewards/gameplay_scores/mean": 0.9875,
      "rewards/gameplay_scores/std": 7.582411861419677,
      "rewards/valid_json_reward/mean": 1.9375,
      "rewards/valid_json_reward/std": 0.25,
      "step": 60
    },
    {
      "clip_ratio/high_max": 0.0,
      "clip_ratio/high_mean": 0.0,
      "clip_ratio/low_mean": 0.0,
      "clip_ratio/low_min": 0.0,
      "clip_ratio/region_mean": 0.0,
      "completions/clipped_ratio": 0.94375,
      "completions/max_length": 128.0,
      "completions/max_terminated_length": 78.6,
      "completions/mean_length": 127.025,
      "completions/mean_terminated_length": 77.53333358764648,
      "completions/min_length": 114.9,
      "completions/min_terminated_length": 76.5,
      "entropy": 1.1606075465679169,
      "epoch": 0.08177570093457943,
      "frac_reward_zero_std": 0.5,
      "grad_norm": 0.0,
      "learning_rate": 4.3100000000000004e-05,
      "loss": 0.0007,
      "num_tokens": 584483.0,
      "reward": -7.775,
      "reward_std": 7.878283357620239,
      "rewards/gameplay_scores/mean": -9.775,
      "rewards/gameplay_scores/std": 19.484172344207764,
      "rewards/valid_json_reward/mean": 2.0,
      "rewards/valid_json_reward/std": 0.0,
      "step": 70
    },
    {
      "clip_ratio/high_max": 0.0,
      "clip_ratio/high_mean": 0.0,
      "clip_ratio/low_mean": 0.0,
      "clip_ratio/low_min": 0.0,
      "clip_ratio/region_mean": 0.0,
      "completions/clipped_ratio": 0.95625,
      "completions/max_length": 128.0,
      "completions/max_terminated_length": 41.7,
      "completions/mean_length": 126.575,
      "completions/mean_terminated_length": 39.266667175292966,
      "completions/min_length": 113.4,
      "completions/min_terminated_length": 36.6,
      "entropy": 1.1126408845186233,
      "epoch": 0.09345794392523364,
      "frac_reward_zero_std": 0.7,
      "grad_norm": 0.0,
      "learning_rate": 4.21e-05,
      "loss": 0.0007,
      "num_tokens": 667047.0,
      "reward": 4.6875,
      "reward_std": 4.92253303527832,
      "rewards/gameplay_scores/mean": 2.8125,
      "rewards/gameplay_scores/std": 8.6554518699646,
      "rewards/valid_json_reward/mean": 1.875,
      "rewards/valid_json_reward/std": 0.5,
      "step": 80
    },
    {
      "clip_ratio/high_max": 0.0,
      "clip_ratio/high_mean": 0.0,
      "clip_ratio/low_mean": 0.0,
      "clip_ratio/low_min": 0.0,
      "clip_ratio/region_mean": 0.0,
      "completions/clipped_ratio": 0.95625,
      "completions/max_length": 128.0,
      "completions/max_terminated_length": 81.8,
      "completions/mean_length": 127.5125,
      "completions/mean_terminated_length": 81.8,
      "completions/min_length": 120.2,
      "completions/min_terminated_length": 81.8,
      "entropy": 1.0793683305382729,
      "epoch": 0.10514018691588785,
      "frac_reward_zero_std": 0.75,
      "grad_norm": 0.66015625,
      "learning_rate": 4.11e-05,
      "loss": -0.0006,
      "num_tokens": 750297.0,
      "reward": -8.3375,
      "reward_std": 4.155660772323609,
      "rewards/gameplay_scores/mean": -10.3375,
      "rewards/gameplay_scores/std": 18.433328247070314,
      "rewards/valid_json_reward/mean": 2.0,
      "rewards/valid_json_reward/std": 0.0,
      "step": 90
    },
    {
      "clip_ratio/high_max": 0.0,
      "clip_ratio/high_mean": 0.0,
      "clip_ratio/low_mean": 0.0,
      "clip_ratio/low_min": 0.0,
      "clip_ratio/region_mean": 0.0,
      "completions/clipped_ratio": 0.95,
      "completions/max_length": 128.0,
      "completions/max_terminated_length": 54.2,
      "completions/mean_length": 126.16875,
      "completions/mean_terminated_length": 53.0,
      "completions/min_length": 103.0,
      "completions/min_terminated_length": 51.8,
      "entropy": 1.104129007458687,
      "epoch": 0.11682242990654206,
      "frac_reward_zero_std": 0.6,
      "grad_norm": 0.74609375,
      "learning_rate": 4.0100000000000006e-05,
      "loss": -0.0002,
      "num_tokens": 833180.0,
      "reward": 1.9375,
      "reward_std": 5.94505467414856,
      "rewards/gameplay_scores/mean": 0.0,
      "rewards/gameplay_scores/std": 13.74187774658203,
      "rewards/valid_json_reward/mean": 1.9375,
      "rewards/valid_json_reward/std": 0.25,
      "step": 100
    }
  ],
  "logging_steps": 10,
  "max_steps": 500,
  "num_input_tokens_seen": 833180,
  "num_train_epochs": 1,
  "save_steps": 100,
  "stateful_callbacks": {
    "TrainerControl": {
      "args": {
        "should_epoch_stop": false,
        "should_evaluate": false,
        "should_log": false,
        "should_save": true,
        "should_training_stop": false
      },
      "attributes": {}
    }
  },
  "total_flos": 0.0,
  "train_batch_size": 4,
  "trial_name": null,
  "trial_params": null
}
